setup.py
pcit/IndependenceTest.py
pcit/MetaEstimator.py
pcit/StructureEstimation.py
pcit/Support.py
pcit/__init__.py
pcit.egg-info/PKG-INFO
pcit.egg-info/SOURCES.txt
pcit.egg-info/dependency_links.txt
pcit.egg-info/top_level.txt