Metadata-Version: 1.0
Name: pcit
Version: 1.2.2
Summary: Predictive Conditional Independence Testing
Home-page: https://github.com/SamBurkart/pcit
Author: Samuel Burkart
Author-email: samuel.burkart@aol.com
License: MIT
Platform: UNKNOWN
